{"stats":{"minecraft:custom":{"minecraft:time_since_rest":224130,"minecraft:sprint_one_cm":1145,"minecraft:walk_one_cm":491929,"minecraft:fly_one_cm":45523,"minecraft:open_chest":8,"minecraft:fill_cauldron":5,"minecraft:crouch_one_cm":950,"minecraft:play_one_minute":224130,"minecraft:sneak_time":793,"minecraft:walk_under_water_one_cm":809,"minecraft:pot_flower":2,"minecraft:jump":148,"minecraft:interact_with_blast_furnace":1,"minecraft:leave_game":1,"minecraft:time_since_death":224130,"minecraft:walk_on_water_one_cm":2642},"minecraft:used":{"minecraft:light_blue_carpet":24,"minecraft:jungle_leaves":3,"minecraft:light_blue_banner":6,"minecraft:dark_oak_stairs":21,"minecraft:water_bucket":39,"minecraft:flower_pot":2,"minecraft:end_rod":3,"minecraft:sea_lantern":40,"minecraft:black_concrete":40,"minecraft:granite_stairs":8,"minecraft:light_gray_concrete":4,"minecraft:lime_carpet":11,"minecraft:light_gray_stained_glass_pane":41,"minecraft:snow_block":11,"minecraft:gray_stained_glass_pane":2,"minecraft:command_block":3,"minecraft:quartz_slab":14,"minecraft:birch_planks":126,"minecraft:stripped_birch_log":2,"minecraft:light_gray_carpet":9,"minecraft:oak_sign":7,"minecraft:cyan_bed":3,"minecraft:polished_andesite":67,"minecraft:lime_wool":53,"minecraft:prismarine_stairs":14,"minecraft:bone_block":7,"minecraft:cyan_carpet":6,"minecraft:quartz_block":23,"minecraft:blue_wool":2,"minecraft:black_carpet":1,"minecraft:white_concrete_powder":119,"minecraft:chest":2,"minecraft:light_blue_bed":2,"minecraft:stone":6,"minecraft:spruce_trapdoor":7,"minecraft:creeper_head":3,"minecraft:smooth_quartz":33,"minecraft:cauldron":5,"minecraft:quartz_stairs":11,"minecraft:barrel":3,"minecraft:yellow_wool":11,"minecraft:white_wool":9,"minecraft:torch":3,"minecraft:tripwire_hook":2,"minecraft:glowstone":4,"minecraft:red_carpet":12,"minecraft:brown_carpet":4,"minecraft:stripped_dark_oak_log":14,"minecraft:iron_trapdoor":7,"minecraft:lime_bed":4,"minecraft:dark_oak_fence":2,"minecraft:red_banner":8,"minecraft:prismarine_brick_stairs":2,"minecraft:blast_furnace":2,"minecraft:repeating_command_block":9,"minecraft:cyan_banner":4,"minecraft:white_concrete":851,"minecraft:painting":84,"minecraft:mushroom_stem":2,"minecraft:dark_oak_door":8,"minecraft:stripped_spruce_wood":8,"minecraft:polished_diorite":81},"minecraft:mined":{"minecraft:lime_bed":2,"minecraft:light_blue_bed":2,"minecraft:cyan_bed":3},"minecraft:picked_up":{"minecraft:black_carpet":1,"minecraft:painting":2,"minecraft:light_gray_carpet":3}},"DataVersion":2227}